{"name":"d49821a88fac6ca7ee664e573647c3a5","link":"#d49821a88fac6ca7ee664e573647c3a5","title":"(no title)","description":"Your have the design, your have the code","keywords":"create page, page builder, simple website","blocks":{"9e3980":{"code":"header","style":"style-6","status":1,"order":6,"params":{"logo":{"type":"image","link":"#","value":"Logo-il-light.png"},"menu-button":{"type":"link","class":"btn btn-success btn-sm","text":"Call To Action","link":"#"},"slider":{"type":"list","class":"carousel-inner screen-height","html_tag":"div","control_button":{"class":"carousel-indicators","items_attr":"data-target='#carousel-unique-{{ block-id }}' data-slide-to='{% index %}' class='{% class %}'"},"items":[{"item_class":"active","background-image":{"type":"background","value":"img-slide-1.jpg","class":"section-background background-size-cover col-xs-12","opacity":0.6,"background-position":"center center"},"title":{"value":"We're just enthusiastic about what we do.","type":"text"},"desctiption":{"value":"And no, we don't know where it will lead. We just know there's something much bigger than any of us here.","type":"text"},"button":{"link":"#button","text":"Sign Up Free","type":"link","class":"btn btn-primary"}},{"item_class":"","background-image":{"type":"background","value":"img-slide-2.jpg","class":"section-background background-size-cover col-xs-12","opacity":0.6,"background-position":"center center"},"title":{"value":"We're just enthusiastic about what we do.","type":"text"},"desctiption":{"value":"And no, we don't know where it will lead. We just know there's something much bigger than any of us here.","type":"text"},"button":{"link":"#button","text":"Sign Up Free","type":"link","class":"btn btn-primary"}}]}}}}}